[{"BillerId":"459","PaymentItemName":"GOtv","BillerName":"GoTV","PaymentAmount":"120000","BillerShortName":"GTV","PaymentItemCode":"112"},{"BillerId":"459","PaymentItemName":"GOtvplus","BillerName":"GoTV","PaymentAmount":"180000","BillerShortName":"GTV","PaymentItemCode":"111"},{"BillerId":"459","PaymentItemName":"GOtv Mobile ","BillerName":"GoTV","PaymentAmount":"60000","BillerShortName":"GTV","PaymentItemCode":"113"},{"BillerId":"459","PaymentItemName":"GOtv Open","BillerName":"GoTV","PaymentAmount":"660000","BillerShortName":"GTV","PaymentItemCode":"114"},{"BillerId":"104","PaymentItemName":"ACCESS BOUQUET","BillerName":"DSTV Subscription","PaymentAmount":"180000","BillerShortName":"DSTV","PaymentItemCode":"28"},{"BillerId":"104","PaymentItemName":"ACCESS BOUQUET + EXTRA VIEW","BillerName":"DSTV Subscription","PaymentAmount":"396000","BillerShortName":"DSTV","PaymentItemCode":"34"},{"BillerId":"104","PaymentItemName":"ACCESS BOUQUET + ASIA","BillerName":"DSTV Subscription","PaymentAmount":"660000","BillerShortName":"DSTV","PaymentItemCode":"32"},{"BillerId":"104","PaymentItemName":"ACCESS BOUQUET + DUAL","BillerName":"DSTV Subscription","PaymentAmount":"396000","BillerShortName":"DSTV","PaymentItemCode":"29"},{"BillerId":"104","PaymentItemName":"ACCESS BOUQUET + FRENCH","BillerName":"DSTV Subscription","PaymentAmount":"755000","BillerShortName":"DSTV","PaymentItemCode":"33"},{"BillerId":"104","PaymentItemName":"ACCESS BOUQUET + PVR ACCESS","BillerName":"DSTV Subscription","PaymentAmount":"396000","BillerShortName":"DSTV","PaymentItemCode":"35"},{"BillerId":"104","PaymentItemName":"HDPVR Access\/Extraview","BillerName":"DSTV Subscription","PaymentAmount":"216000","BillerShortName":"DSTV","PaymentItemCode":"36"},{"BillerId":"104","PaymentItemName":"ASIAN BOUQUET","BillerName":"DSTV Subscription","PaymentAmount":"480000","BillerShortName":"DSTV","PaymentItemCode":"17"},{"BillerId":"104","PaymentItemName":"ASIAN BOUQUET + DUAL","BillerName":"DSTV Subscription","PaymentAmount":"580000","BillerShortName":"DSTV","PaymentItemCode":"20"},{"BillerId":"104","PaymentItemName":"ASIAN BOUQUET + PVR ACCESS","BillerName":"DSTV Subscription","PaymentAmount":"696000","BillerShortName":"DSTV","PaymentItemCode":"60"},{"BillerId":"104","PaymentItemName":"ASIAN BOUQUET + EXTRA VIEW","BillerName":"DSTV Subscription","PaymentAmount":"580000","BillerShortName":"DSTV","PaymentItemCode":"59"},{"BillerId":"104","PaymentItemName":"BOX OFFICE","BillerName":"DSTV Subscription","PaymentAmount":"0","BillerShortName":"DSTV","PaymentItemCode":"115"},{"BillerId":"104","PaymentItemName":"FAMILY + EXTRA VIEW","BillerName":"DSTV Subscription","PaymentAmount":"576000","BillerShortName":"DSTV","PaymentItemCode":"40"},{"BillerId":"104","PaymentItemName":"FAMILY BOUQUET","BillerName":"DSTV Subscription","PaymentAmount":"360000","BillerShortName":"DSTV","PaymentItemCode":"06"},{"BillerId":"104","PaymentItemName":"FAMILY + ASIA","BillerName":"DSTV Subscription","PaymentAmount":"840000","BillerShortName":"DSTV","PaymentItemCode":"37"},{"BillerId":"104","PaymentItemName":"FAMILY + DUAL","BillerName":"DSTV Subscription","PaymentAmount":"576000","BillerShortName":"DSTV","PaymentItemCode":"25"},{"BillerId":"104","PaymentItemName":"FAMILY + PVR ACCESS","BillerName":"DSTV Subscription","PaymentAmount":"576000","BillerShortName":"DSTV","PaymentItemCode":"10"},{"BillerId":"104","PaymentItemName":"FAMILY + GERMAN","BillerName":"DSTV Subscription","PaymentAmount":"664000","BillerShortName":"DSTV","PaymentItemCode":"38"},{"BillerId":"104","PaymentItemName":"COMPACT PLUS BOUQUET","BillerName":"DSTV Subscription","PaymentAmount":"942000","BillerShortName":"DSTV","PaymentItemCode":"30"},{"BillerId":"104","PaymentItemName":"COMPACT PLUS + EXTRA VIEW","BillerName":"DSTV Subscription","PaymentAmount":"1158000","BillerShortName":"DSTV","PaymentItemCode":"50"},{"BillerId":"104","PaymentItemName":"COMPACT PLUS + ASIA","BillerName":"DSTV Subscription","PaymentAmount":"1422000","BillerShortName":"DSTV","PaymentItemCode":"45"},{"BillerId":"104","PaymentItemName":"COMPACT PLUS + ASIA + DUAL VIEW","BillerName":"DSTV Subscription","PaymentAmount":"1638000","BillerShortName":"DSTV","PaymentItemCode":"53"},{"BillerId":"104","PaymentItemName":"COMPACT PLUS+ ASIA+PVR ACCESS","BillerName":"DSTV Subscription","PaymentAmount":"1638000","BillerShortName":"DSTV","PaymentItemCode":"52"},{"BillerId":"104","PaymentItemName":"COMPACT PLUS + ASIA + ZDF","BillerName":"DSTV Subscription","PaymentAmount":"1786000","BillerShortName":"DSTV","PaymentItemCode":"46"},{"BillerId":"104","PaymentItemName":"COMPACT PLUS + DUAL VIEW","BillerName":"DSTV Subscription","PaymentAmount":"1158000","BillerShortName":"DSTV","PaymentItemCode":"49"},{"BillerId":"104","PaymentItemName":"COMPACT PLUS + FRENCH","BillerName":"DSTV Subscription","PaymentAmount":"1194000","BillerShortName":"DSTV","PaymentItemCode":"48"},{"BillerId":"104","PaymentItemName":"COMPACT PLUS + PVR ACCESS","BillerName":"DSTV Subscription","PaymentAmount":"1158000","BillerShortName":"DSTV","PaymentItemCode":"51"},{"BillerId":"104","PaymentItemName":"COMPACT PLUS + GERMAN","BillerName":"DSTV Subscription","PaymentAmount":"1306000","BillerShortName":"DSTV","PaymentItemCode":"47"},{"BillerId":"104","PaymentItemName":"Premium + French Touch","BillerName":"DSTV Subscription","PaymentAmount":"1538000","BillerShortName":"DSTV","PaymentItemCode":"15"},{"BillerId":"104","PaymentItemName":"COMPACT+ PVR ACCESS","BillerName":"DSTV Subscription","PaymentAmount":"1296000","BillerShortName":"DSTV","PaymentItemCode":"64"},{"BillerId":"104","PaymentItemName":"COMPACT","BillerName":"DSTV Subscription","PaymentAmount":"600000","BillerShortName":"DSTV","PaymentItemCode":"03"},{"BillerId":"104","PaymentItemName":"COMPACT + EXTRA VIEW","BillerName":"DSTV Subscription","PaymentAmount":"816000","BillerShortName":"DSTV","PaymentItemCode":"43"},{"BillerId":"104","PaymentItemName":"COMPACT + ASIA +GERMAN","BillerName":"DSTV Subscription","PaymentAmount":"1444000","BillerShortName":"DSTV","PaymentItemCode":"42"},{"BillerId":"104","PaymentItemName":"COMPACT + ASIA","BillerName":"DSTV Subscription","PaymentAmount":"1080000","BillerShortName":"DSTV","PaymentItemCode":"22"},{"BillerId":"104","PaymentItemName":"COMPACT + ASIA + DUAL","BillerName":"DSTV Subscription","PaymentAmount":"1296000","BillerShortName":"DSTV","PaymentItemCode":"62"},{"BillerId":"104","PaymentItemName":"COMPACT + FRENCH","BillerName":"DSTV Subscription","PaymentAmount":"1004000","BillerShortName":"DSTV","PaymentItemCode":"44"},{"BillerId":"104","PaymentItemName":"COMPACT + HDPVR","BillerName":"DSTV Subscription","PaymentAmount":"816000","BillerShortName":"DSTV","PaymentItemCode":"09"},{"BillerId":"104","PaymentItemName":"Mobile Maxi Plus","BillerName":"DSTV Subscription","PaymentAmount":"99000","BillerShortName":"DSTV","PaymentItemCode":"63"},{"BillerId":"104","PaymentItemName":"PREMIUM + DUAL","BillerName":"DSTV Subscription","PaymentAmount":"1614000","BillerShortName":"DSTV","PaymentItemCode":"02"},{"BillerId":"104","PaymentItemName":"PREMIUM + ASIA","BillerName":"DSTV Subscription","PaymentAmount":"1574000","BillerShortName":"DSTV","PaymentItemCode":"18"},{"BillerId":"104","PaymentItemName":"PREMIUM + ASIA + PVR ACCESS","BillerName":"DSTV Subscription","PaymentAmount":"1790000","BillerShortName":"DSTV","PaymentItemCode":"57"},{"BillerId":"104","PaymentItemName":"PREMIUM + ASIA + DUAL","BillerName":"DSTV Subscription","PaymentAmount":"1790000","BillerShortName":"DSTV","PaymentItemCode":"26"},{"BillerId":"104","PaymentItemName":"PREMIUM + FRENCH","BillerName":"DSTV Subscription","PaymentAmount":"1968000","BillerShortName":"DSTV","PaymentItemCode":"14"},{"BillerId":"104","PaymentItemName":"PREMIUM + FRENCH + ASIA","BillerName":"DSTV Subscription","PaymentAmount":"1712000","BillerShortName":"DSTV","PaymentItemCode":"54"},{"BillerId":"104","PaymentItemName":"PREMIUM + FRENCH + ASIA +GERMAN","BillerName":"DSTV Subscription","PaymentAmount":"2642000","BillerShortName":"DSTV","PaymentItemCode":"55"},{"BillerId":"104","PaymentItemName":"PREMIUM + FRENCH + DUAL","BillerName":"DSTV Subscription","PaymentAmount":"2184000","BillerShortName":"DSTV","PaymentItemCode":"27"},{"BillerId":"104","PaymentItemName":"PREMIUM","BillerName":"DSTV Subscription","PaymentAmount":"1398000","BillerShortName":"DSTV","PaymentItemCode":"01"},{"BillerId":"104","PaymentItemName":"PREMIUM + EXTRA VIEW","BillerName":"DSTV Subscription","PaymentAmount":"1614000","BillerShortName":"DSTV","PaymentItemCode":"56"},{"BillerId":"104","PaymentItemName":"PREMIUM + PVR ACCESS","BillerName":"DSTV Subscription","PaymentAmount":"1614000","BillerShortName":"DSTV","PaymentItemCode":"08"},{"BillerId":"104","PaymentItemName":"Premium Asia + HD\/ExtraView","BillerName":"DSTV Subscription","PaymentAmount":"1790000","BillerShortName":"DSTV","PaymentItemCode":"21"},{"BillerId":"104","PaymentItemName":"GERMAN ALONE","BillerName":"DSTV Subscription","PaymentAmount":"364000","BillerShortName":"DSTV","PaymentItemCode":"11"},{"BillerId":"101","PaymentItemName":"Startimes Bouquet","BillerName":"Startimes Payment","PaymentAmount":"0","BillerShortName":"STRC","PaymentItemCode":"99"},{"BillerId":"459","PaymentItemName":"GOTV Lite Annual","BillerName":"GoTV","PaymentAmount":"310000","BillerShortName":"GTV","PaymentItemCode":"115"},{"BillerId":"459","PaymentItemName":"GOTV Lite Quarterly","BillerName":"GoTV","PaymentAmount":"105000","BillerShortName":"GTV","PaymentItemCode":"116"},{"BillerId":"459","PaymentItemName":"GOTV Lite Monthly","BillerName":"GoTV","PaymentAmount":"40000","BillerShortName":"GTV","PaymentItemCode":"117"},{"BillerId":"104","PaymentItemName":"French Plus","BillerName":"DSTV Subscription","PaymentAmount":"605000","BillerShortName":"DSTV","PaymentItemCode":"101"},{"BillerId":"104","PaymentItemName":"French Touch","BillerName":"DSTV Subscription","PaymentAmount":"140000","BillerShortName":"DSTV","PaymentItemCode":"102"},{"BillerId":"104","PaymentItemName":"Compact + French Touch","BillerName":"DSTV Subscription","PaymentAmount":"740000","BillerShortName":"DSTV","PaymentItemCode":"139"},{"BillerId":"104","PaymentItemName":"Compact + French Touch + HD\/ExtraView","BillerName":"DSTV Subscription","PaymentAmount":"956000","BillerShortName":"DSTV","PaymentItemCode":"140"},{"BillerId":"104","PaymentItemName":"Mobile Mini","BillerName":"DSTV Subscription","PaymentAmount":"60000","BillerShortName":"DSTV","PaymentItemCode":"75"},{"BillerId":"104","PaymentItemName":"Mobile Maxi","BillerName":"DSTV Subscription","PaymentAmount":"79000","BillerShortName":"DSTV","PaymentItemCode":"76"},{"BillerId":"104","PaymentItemName":"Premium + Asia","BillerName":"DSTV Subscription","PaymentAmount":"1574000","BillerShortName":"DSTV","PaymentItemCode":"133"},{"BillerId":"104","PaymentItemName":"Premium + French Touch + HD\/ExtraView","BillerName":"DSTV Subscription","PaymentAmount":"1754000","BillerShortName":"DSTV","PaymentItemCode":"141"},{"BillerId":"104","PaymentItemName":"Premium + HD\/ExtraView","BillerName":"DSTV Subscription","PaymentAmount":"1614000","BillerShortName":"DSTV","PaymentItemCode":"58"},{"BillerId":"104","PaymentItemName":"GERMAN (FOR PREMIUM SUBSCRIBERS)","BillerName":"DSTV Subscription","PaymentAmount":"194000","BillerShortName":"DSTV","PaymentItemCode":"103"}]